sphinxcontrib_srclinks-0.2.4-py3.7-nspkg.pth
sphinxcontrib_srclinks-0.2.4.dist-info/top_level.txt
sphinxcontrib_srclinks-0.2.4.dist-info/WHEEL
sphinxcontrib_srclinks-0.2.4.dist-info/namespace_packages.txt
sphinxcontrib_srclinks-0.2.4.dist-info/pydist.json
sphinxcontrib_srclinks-0.2.4.dist-info/RECORD
sphinxcontrib_srclinks-0.2.4.dist-info/METADATA
sphinxcontrib_srclinks-0.2.4.dist-info/DESCRIPTION.rst
sphinxcontrib/srclinks/__init__.py
sphinxcontrib/srclinks/_templates/srclinks.html
