Metadata-Version: 2.0
Name: sphinxcontrib-srclinks
Version: 0.2.4
Summary: Add source, edit, history, annotate links to GitHub or BitBucket
Home-page: http://bitbucket.org/westurner/sphinxcontrib-srclinks
Author: Wes Turner
Author-email: wes@wrd.nu
License: BSD (3-clause)
Download-URL: http://pypi.python.org/pypi/sphinxcontrib-srclinks
Platform: any
Classifier: Development Status :: 4 - Beta
Classifier: Environment :: Web Environment
Classifier: Intended Audience :: Developers
Classifier: License :: OSI Approved :: BSD License
Classifier: Operating System :: OS Independent
Classifier: Programming Language :: Python
Classifier: Programming Language :: Python :: 2
Classifier: Programming Language :: Python :: 3
Classifier: Topic :: Documentation
Classifier: Topic :: Utilities
Requires-Dist: Sphinx (>=0.6)
